{
  "game_info": {
    "scenario": "HJ vs BTN",
    "node_path": "hjr_btnr_hjr_btnai_hj",
    "step": 5,
    "hero_position": "HJ",
    "active_positions": [
      "HJ",
      "BTN"
    ],
    "folded_positions": [
      "UTG",
      "CO",
      "SB",
      "BB"
    ],
    "action_history": [
      {
        "position": "UTG",
        "action": "Fold"
      },
      {
        "position": "HJ",
        "action": "Raise 2.5"
      },
      {
        "position": "CO",
        "action": "Fold"
      },
      {
        "position": "BTN",
        "action": "Raise 7.5"
      },
      {
        "position": "SB",
        "action": "Fold"
      },
      {
        "position": "BB",
        "action": "Fold"
      },
      {
        "position": "HJ",
        "action": "Raise 20"
      },
      {
        "position": "BTN",
        "action": "Allin 100"
      }
    ],
    "is_leaf": true,
    "available_actions_at_this_node": [
      "Call",
      "Fold"
    ],
    "solution": {
      "game_type": "Cash",
      "stack": "100bb",
      "players": "6max",
      "rake": "NL500",
      "type": "Classic",
      "opening_size": "2.5x",
      "bet_sizes": "General",
      "postflop_bet_sizes": "Multi Size"
    }
  },
  "actions_legend": {
    "allin": "all-in",
    "raise": "raise (all sizes combined)",
    "call": "call",
    "fold": "fold"
  },
  "hands": {
    "77": {
      "allin": 0,
      "raise": 0,
      "call": 0,
      "fold": 100
    },
    "88": {
      "allin": 0,
      "raise": 0,
      "call": 0,
      "fold": 100
    },
    "99": {
      "allin": 0,
      "raise": 0,
      "call": 0,
      "fold": 100
    },
    "AA": {
      "allin": 0,
      "raise": 0,
      "call": 100,
      "fold": 0
    },
    "AKs": {
      "allin": 0,
      "raise": 0,
      "call": 100,
      "fold": 0
    },
    "AQs": {
      "allin": 0,
      "raise": 0,
      "call": 0,
      "fold": 100
    },
    "AJs": {
      "allin": 0,
      "raise": 0,
      "call": 0,
      "fold": 100
    },
    "ATs": {
      "allin": 0,
      "raise": 0,
      "call": 0,
      "fold": 100
    },
    "A8s": {
      "allin": 0,
      "raise": 0,
      "call": 0,
      "fold": 100
    },
    "A5s": {
      "allin": 0,
      "raise": 0,
      "call": 0,
      "fold": 100
    },
    "A4s": {
      "allin": 0,
      "raise": 0,
      "call": 0,
      "fold": 100
    },
    "AKo": {
      "allin": 0,
      "raise": 0,
      "call": 100,
      "fold": 0
    },
    "KK": {
      "allin": 0,
      "raise": 0,
      "call": 100,
      "fold": 0
    },
    "KQs": {
      "allin": 0,
      "raise": 0,
      "call": 0,
      "fold": 100
    },
    "KJs": {
      "allin": 0,
      "raise": 0,
      "call": 0,
      "fold": 100
    },
    "KTs": {
      "allin": 0,
      "raise": 0,
      "call": 0,
      "fold": 100
    },
    "K6s": {
      "allin": 0,
      "raise": 0,
      "call": 0,
      "fold": 100
    },
    "AQo": {
      "allin": 0,
      "raise": 0,
      "call": 0,
      "fold": 100
    },
    "QQ": {
      "allin": 0,
      "raise": 0,
      "call": 100,
      "fold": 0
    },
    "QJs": {
      "allin": 0,
      "raise": 0,
      "call": 0,
      "fold": 100
    },
    "QTs": {
      "allin": 0,
      "raise": 0,
      "call": 0,
      "fold": 100
    },
    "JJ": {
      "allin": 0,
      "raise": 0,
      "call": 96.6,
      "fold": 3.4
    },
    "JTs": {
      "allin": 0,
      "raise": 0,
      "call": 0,
      "fold": 100
    },
    "TT": {
      "allin": 0,
      "raise": 0,
      "call": 100,
      "fold": 0
    },
    "T9s": {
      "allin": 0,
      "raise": 0,
      "call": 0,
      "fold": 100
    }
  }
}
